cpufreqizer/__init__.py
cpufreqizer/main.py
cpufreqizer/prompts.py
cpufreqizer-2025.12.21234021.dist-info/METADATA
cpufreqizer-2025.12.21234021.dist-info/WHEEL
cpufreqizer-2025.12.21234021.dist-info/top_level.txt
cpufreqizer-2025.12.21234021.dist-info/RECORD
