Metadata-Version: 2.4
Name: cpufreqizer
Version: 2025.12.21234021
Summary: cpufreqizer recommends optimal CPU scaling governors and kernel params based on workload, balancing power and performance.
Author-email: cpufreqizer <hi@eugene.plus>
License: MIT
Project-URL: Homepage, https://github.com/chigwell/cpufreqizer
Requires-Python: >=3.9
Requires-Dist: langchain-llm7>=0.0.0
Requires-Dist: llmatch-messages>=0.0.0
Requires-Dist: langchain-core>=0.3.0
